cyberdbg/__init__.py
cyberdbg/gfg.py
cyberdbg-1.0.2.dist-info/LICENSE
cyberdbg-1.0.2.dist-info/METADATA
cyberdbg-1.0.2.dist-info/WHEEL
cyberdbg-1.0.2.dist-info/entry_points.txt
cyberdbg-1.0.2.dist-info/top_level.txt
cyberdbg-1.0.2.dist-info/RECORD
