Metadata-Version: 2.1
Name: cyberdbg
Version: 1.0.2
Summary: Demo Package for GfG Article.
Home-page: https://github.com/chopstickxs/Cyberdbg
Author: chopstickxs
Author-email: chopstickxs@yandex.com
License: MIT
Keywords: dbg cyber
Platform: UNKNOWN
Classifier: Programming Language :: Python :: 3
Classifier: License :: OSI Approved :: MIT License
Classifier: Operating System :: OS Independent
